SciQLop/__init__.py
SciQLop/app.py
SciQLop/pysidedeploy.spec
SciQLop/sciqlop_app.py
SciQLop/sciqlop_launcher.py
SciQLop/Jupyter/__init__.py
SciQLop/Jupyter/entry_points.txt
SciQLop/Jupyter/lab_kernel_manager.py
SciQLop/backend/__init__.py
SciQLop/backend/check_for_updates.py
SciQLop/backend/enums.py
SciQLop/backend/icons.py
SciQLop/backend/models.py
SciQLop/backend/property.py
SciQLop/backend/sciqlop_application.py
SciQLop/backend/unique_names.py
SciQLop/backend/IPythonKernel/__init__.py
SciQLop/backend/common/ExtraColumnsProxyModel.py
SciQLop/backend/common/__init__.py
SciQLop/backend/common/dataclasses.py
SciQLop/backend/common/pip_process.py
SciQLop/backend/common/process.py
SciQLop/backend/common/python.py
SciQLop/backend/common/signal_rate_limiter.py
SciQLop/backend/common/terminal_messages.py
SciQLop/backend/data_models/__init__.py
SciQLop/backend/data_models/models.py
SciQLop/backend/data_models/serialisation.py
SciQLop/backend/examples/__init__.py
SciQLop/backend/examples/example.py
SciQLop/backend/jupyter_clients/__init__.py
SciQLop/backend/jupyter_clients/clients_manager.py
SciQLop/backend/jupyter_clients/jupyter_client_process.py
SciQLop/backend/jupyter_clients/jupyterlab_auto_build.py
SciQLop/backend/jupyter_clients/jupyterlab_launcher.py
SciQLop/backend/jupyter_clients/qt_console.py
SciQLop/backend/pipelines_model/__init__.py
SciQLop/backend/pipelines_model/data_provider.py
SciQLop/backend/pipelines_model/easy_provider.py
SciQLop/backend/sciqlop_logging/__init__.py
SciQLop/backend/sciqlop_logging/logger.py
SciQLop/backend/settings/__init__.py
SciQLop/backend/theming/__init__.py
SciQLop/backend/theming/loader.py
SciQLop/backend/workspace/__init__.py
SciQLop/backend/workspace/workspace.py
SciQLop/backend/workspace/workspaces_manager.py
SciQLop/examples/PySPEDAS/example.json
SciQLop/examples/PySPEDAS/image.png
SciQLop/examples/PySPEDAS/pyspedas.ipynb
SciQLop/examples/SimpleVirtualProduct/example.json
SciQLop/examples/SimpleVirtualProduct/image.png
sciqlop-0.10.4.dist-info/entry_points.txt
sciqlop-0.10.4.dist-info/licenses/COPYING
sciqlop-0.10.4.dist-info/WHEEL
sciqlop-0.10.4.dist-info/METADATA
sciqlop-0.10.4.dist-info/RECORD
