Metadata-Version: 2.4
Name: SciQLop
Version: 0.10.4
Summary: An ergonomic and efficient application to browse and label in situ plasma measurements from multi-mission satellite data.
Keywords: machine-learning,satellite,plasma-physics,nasa-data,amda,cdpp
Author-email: Alexis Jeandet <alexis.jeandet@member.fsf.org>
Maintainer-email: Alexis Jeandet <alexis.jeandet@member.fsf.org>
Requires-Python: >=3.8
Classifier: Development Status :: 4 - Beta
Classifier: Intended Audience :: Science/Research
Classifier: License :: OSI Approved :: GNU General Public License v3 (GPLv3)
Classifier: Natural Language :: English
Classifier: Programming Language :: Python :: 3
Classifier: Programming Language :: Python :: 3.9
Classifier: Programming Language :: Python :: 3.10
Classifier: Programming Language :: Python :: 3.11
Classifier: Programming Language :: Python :: 3.12
Classifier: Programming Language :: Python :: 3.13
Classifier: Programming Language :: Python :: 3.14
Classifier: Topic :: Scientific/Engineering :: Physics
Classifier: Topic :: Scientific/Engineering :: Visualization
License-File: COPYING
Requires-Dist: SciQLopPlots==0.17.1
Requires-Dist: PySide6-QtAds==4.4.0.3
Requires-Dist: PySide6==6.9.2
Requires-Dist: shiboken6==6.9.2
Requires-Dist: speasy>=1.5.2
Requires-Dist: qtconsole
Requires-Dist: tscat_gui==0.6.*
Requires-Dist: tscat==0.4.*
Requires-Dist: humanize
Requires-Dist: platformdirs
Requires-Dist: seaborn
Requires-Dist: scipy
Requires-Dist: ipython==8.37.0
Requires-Dist: ipykernel==6.29.5
Requires-Dist: ipympl==0.9.7
Requires-Dist: ipywidgets==8.1.7
Requires-Dist: jupyter-events==0.12.0
Requires-Dist: jupyter-lsp==2.2.5
Requires-Dist: jupyter_client==8.6.3
Requires-Dist: jupyter_core==5.8.1
Requires-Dist: jupyter_server==2.16.0
Requires-Dist: jupyter_server_terminals==0.5.3
Requires-Dist: jupyterlab==4.4.4
Requires-Dist: jupyterlab_pygments==0.3.0
Requires-Dist: jupyterlab_server==2.27.3
Requires-Dist: jupyterlab_widgets==3.0.15
Requires-Dist: matplotlib==3.10.3
Requires-Dist: matplotlib-inline==0.1.7
Requires-Dist: notebook==7.4.4
Requires-Dist: notebook_shim==0.2.4
Requires-Dist: tornado==6.5.1
Requires-Dist: pyzmq==27.0.0
Requires-Dist: qasync
Requires-Dist: jinja2
Requires-Dist: pyzstd
Requires-Dist: PyGitHub
Requires-Dist: numpy
Requires-Dist: expression
Requires-Dist: httpx_ws>=0.7.1,<0.8.0
Requires-Dist: pycrdt-websocket>=0.15.4,<0.16.0
Requires-Dist: pycrdt
Requires-Dist: pytest-runner ; extra == "dev"
Requires-Dist: pytest ; extra == "dev"
Requires-Dist: pytest-cov ; extra == "dev"
Requires-Dist: pytest-qt ; extra == "dev"
Requires-Dist: pytest-xvfb ; extra == "dev" and ( platform_system == "Linux")
Project-URL: bug_tracker, https://github.com/SciQLop/SciQLop/issues
Project-URL: homepage, https://github.com/SciQLop/SciQLop
Provides-Extra: dev
